parsewhen/__init__.py
parsewhen/__main__.py
parsewhen/errors.py
parsewhen/eval.py
parsewhen/language.py
parsewhen/lexer.py
parsewhen/parser.py
parsewhen/parsewhen.py
parsewhen/walker.py
parsewhen-0.2.6.dist-info/LICENSE
parsewhen-0.2.6.dist-info/METADATA
parsewhen-0.2.6.dist-info/WHEEL
parsewhen-0.2.6.dist-info/entry_points.txt
parsewhen-0.2.6.dist-info/top_level.txt
parsewhen-0.2.6.dist-info/zip-safe
parsewhen-0.2.6.dist-info/RECORD
