Metadata-Version: 2.1
Name: parsewhen
Version: 0.2.6
Summary: A library for extracting and parsing dates from English sentences.
Home-page: UNKNOWN
Author: UNKNOWN
Author-email: UNKNOWN
License: MIT
Platform: UNKNOWN
